{"pbonn_03490_g":{"exact":[],"prefix":["PBONN_03490_gene"]},"pbonn_03193_gen":{"prefix":["PBONN_03193_gene"],"exact":[]},"pbonn_00708_gen":{"prefix":["PBONN_00708_gene"],"exact":[]},"pbonn_01147_":{"prefix":["PBONN_01147_gene"],"exact":[]},"pbonn_02080_g":{"exact":[],"prefix":["PBONN_02080_gene"]},"pbonn_02122_gene":{"exact":[["PBONN_02122_gene",0,"PBONN_02122_gene","NZ_QPEQ01000001.1",2371546,2372551]],"prefix":[]},"pbonn_00091_":{"prefix":["PBONN_00091_gene"],"exact":[]},"pbonn_03409_":{"prefix":["PBONN_03409_gene"],"exact":[]},"pbonn_02481_":{"exact":[],"prefix":["PBONN_02481_gene"]},"pbonn_01570_ge":{"prefix":["PBONN_01570_gene"],"exact":[]},"pbonn_02154":{"prefix":["PBONN_02154_gene"],"exact":[["PBONN_02154",0,"PBONN_02154_gene","NZ_QPEQ01000001.1",2403813,2404089]]},"pbonn_03458_g":{"prefix":["PBONN_03458_gene"],"exact":[]},"pbonn_00814":{"exact":[["PBONN_00814",0,"PBONN_00814_gene","NZ_QPEQ01000001.1",908583,908982]],"prefix":["PBONN_00814_gene"]},"yqj":{"prefix":["yqjD","yqjC"],"exact":[]},"pbonn_00205_":{"prefix":["PBONN_00205_gene"],"exact":[]},"pbonn_02048_g":{"prefix":["PBONN_02048_gene"],"exact":[]},"pbonn_00643_gene":{"prefix":[],"exact":[["PBONN_00643_gene",0,"ubiJ","NZ_QPEQ01000001.1",723125,723770]]},"pbonn_01856_g":{"prefix":["PBONN_01856_gene"],"exact":[]},"pbonn_01593_":{"exact":[],"prefix":["PBONN_01593_gene"]},"pbonn_01542_gen":{"prefix":["PBONN_01542_gene"],"exact":[]},"pbonn_00463":{"exact":[["PBONN_00463",0,"rplJ","NZ_QPEQ01000001.1",534799,535387]],"prefix":["PBONN_00463_gene"]},"pbonn_02592_gene":{"exact":[["PBONN_02592_gene",0,"PBONN_02592_gene","NZ_QPEQ01000001.1",2899801,2899981]],"prefix":[]},"pbonn_02227_gen":{"prefix":["PBONN_02227_gene"],"exact":[]},"pbonn_02033_ge":{"exact":[],"prefix":["PBONN_02033_gene"]},"pbonn_03557_":{"prefix":["PBONN_03557_gene"],"exact":[]},"pbonn_02209_g":{"exact":[],"prefix":["PBONN_02209_gene"]},"pbonn_03176_gen":{"prefix":["PBONN_03176_gene"],"exact":[]},"pbonn_02671_gen":{"exact":[],"prefix":["PBONN_02671_gene"]},"pbonn_02694_gen":{"prefix":["PBONN_02694_gene"],"exact":[]},"pbonn_00060_gene":{"prefix":[],"exact":[["PBONN_00060_gene",0,"PBONN_00060_gene","NZ_QPEQ01000001.1",69088,71500]]},"pbonn_01114_gen":{"prefix":["PBONN_01114_gene"],"exact":[]},"pbonn_01459_gen":{"exact":[],"prefix":["PBONN_01459_gene"]},"pbonn_01019_":{"exact":[],"prefix":["PBONN_01019_gene"]},"pbonn_03267_gene":{"prefix":[],"exact":[["PBONN_03267_gene",0,"PBONN_03267_gene","NZ_QPEQ01000002.1",517475,517934]]},"pbonn_028":{"prefix":["PBONN_02800_gene","PBONN_02801_gene","PBONN_02801","PBONN_02802_gene","PBONN_02802","PBONN_02803_gene","PBONN_02803","PBONN_02804_gene","PBONN_02804","PBONN_02805_gene","PBONN_02805","PBONN_02806_gene","PBONN_02806","PBONN_02807_gene","PBONN_02807","PBONN_02808_gene","PBONN_02808","PBONN_02809_gene","PBONN_02809","PBONN_02810_gene",{"name":"too many matches","hitLimit":1}],"exact":[]},"pbonn_01700":{"prefix":["PBONN_01700_gene"],"exact":[["PBONN_01700",0,"PBONN_01700_gene","NZ_QPEQ01000001.1",1923021,1924404]]},"otnk":{"exact":[["otnK",0,"otnK","NZ_QPEQ01000002.1",381364,382732]],"prefix":[]},"pbonn_02615_":{"prefix":["PBONN_02615_gene"],"exact":[]},"pbonn_03237":{"prefix":["PBONN_03237_gene"],"exact":[["PBONN_03237",0,"lcdH","NZ_QPEQ01000002.1",464069,464597]]},"pbonn_02479_gene":{"prefix":[],"exact":[["PBONN_02479_gene",0,"yceI_1","NZ_QPEQ01000001.1",2776909,2777488]]},"pbonn_03519":{"exact":[["PBONN_03519",0,"PBONN_03519_gene","NZ_QPEQ01000002.1",817249,817618]],"prefix":["PBONN_03519_gene"]},"pbonn_0148":{"prefix":["PBONN_01480_gene","PBONN_01480","PBONN_01481_gene","PBONN_01481","PBONN_01482_gene","PBONN_01482","PBONN_01483_gene","PBONN_01483","PBONN_01484_gene","PBONN_01484","PBONN_01485_gene","PBONN_01485","PBONN_01486_gene","PBONN_01486","PBONN_01487_gene","PBONN_01487","PBONN_01488_gene","PBONN_01488","PBONN_01489_gene","PBONN_01489"],"exact":[]},"pbonn_01913_":{"exact":[],"prefix":["PBONN_01913_gene"]},"pbonn_03148_ge":{"exact":[],"prefix":["PBONN_03148_gene"]},"pbonn_00111":{"prefix":["PBONN_00111_gene"],"exact":[["PBONN_00111",0,"tssK-1","NZ_QPEQ01000001.1",113745,115092]]},"pbonn_03249_":{"exact":[],"prefix":["PBONN_03249_gene"]},"tsse":{"exact":[],"prefix":["tssE-5"]},"pbonn_01795_gene":{"exact":[["PBONN_01795_gene",0,"PBONN_01795_gene","NZ_QPEQ01000001.1",2039802,2040705]],"prefix":[]},"pbonn_0314":{"prefix":["PBONN_03140_gene","PBONN_03140","PBONN_03141_gene","PBONN_03141","PBONN_03142_gene","PBONN_03142","PBONN_03143_gene","PBONN_03143","PBONN_03144_gene","PBONN_03144","PBONN_03145_gene","PBONN_03145","PBONN_03146_gene","PBONN_03146","PBONN_03147_gene","PBONN_03147","PBONN_03148_gene","PBONN_03148","PBONN_03149_gene","PBONN_03149"],"exact":[]},"pbonn_01659_":{"exact":[],"prefix":["PBONN_01659_gene"]},"pbonn_00792":{"prefix":["PBONN_00792_gene"],"exact":[["PBONN_00792",0,"PBONN_00792_gene","NZ_QPEQ01000001.1",889806,890169]]},"prpb":{"prefix":["prpB_1","prpB_2"],"exact":[]},"pbonn_02701_gene":{"exact":[["PBONN_02701_gene",0,"gpmA","NZ_QPEQ01000001.1",3011259,3012075]],"prefix":[]},"pbonn_02055_":{"exact":[],"prefix":["PBONN_02055_gene"]},"pbonn_01482_g":{"prefix":["PBONN_01482_gene"],"exact":[]},"pbonn_02851":{"exact":[["PBONN_02851",0,"PBONN_02851_gene","NZ_QPEQ01000002.1",9105,9954]],"prefix":["PBONN_02851_gene"]},"pbonn_02801_":{"exact":[],"prefix":["PBONN_02801_gene"]},"pbonn_01325_gene":{"exact":[["PBONN_01325_gene",0,"PBONN_01325_gene","NZ_QPEQ01000001.1",1492895,1494254]],"prefix":[]},"pbonn_01272":{"exact":[["PBONN_01272",0,"PBONN_01272_gene","NZ_QPEQ01000001.1",1421352,1422900]],"prefix":["PBONN_01272_gene"]},"pbonn_03520_gen":{"exact":[],"prefix":["PBONN_03520_gene"]},"pbonn_02853_gene":{"prefix":[],"exact":[["PBONN_02853_gene",0,"shc","NZ_QPEQ01000002.1",11221,13261]]},"pbonn_02308":{"prefix":["PBONN_02308_gene"],"exact":[["PBONN_02308",0,"fusA_2","NZ_QPEQ01000001.1",2570150,2572256]]},"pbonn_02172_ge":{"prefix":["PBONN_02172_gene"],"exact":[]},"pbonn_01832_g":{"prefix":["PBONN_01832_gene"],"exact":[]},"pbonn_01846_gen":{"exact":[],"prefix":["PBONN_01846_gene"]},"pbonn_00445_":{"prefix":["PBONN_00445_gene"],"exact":[]},"pbonn_01506_gene":{"exact":[["PBONN_01506_gene",0,"recR","NZ_QPEQ01000001.1",1692413,1693010]],"prefix":[]},"pbonn_01183":{"prefix":["PBONN_01183_gene"],"exact":[["PBONN_01183",0,"PBONN_01183_gene","NZ_QPEQ01000001.1",1327078,1327300]]},"pbonn_03183_ge":{"prefix":["PBONN_03183_gene"],"exact":[]},"pbonn_03009_ge":{"exact":[],"prefix":["PBONN_03009_gene"]},"qmca":{"exact":[["qmcA",0,"qmcA","NZ_QPEQ01000001.1",1980223,1981156]],"prefix":[]},"pbonn_00092_g":{"exact":[],"prefix":["PBONN_00092_gene"]},"pbonn_00318_gene":{"exact":[["PBONN_00318_gene",0,"cheZ","NZ_QPEQ01000001.1",373897,374644]],"prefix":[]},"pbonn_00245_gen":{"prefix":["PBONN_00245_gene"],"exact":[]},"pbonn_03444_gene":{"prefix":[],"exact":[["PBONN_03444_gene",0,"talB","NZ_QPEQ01000002.1",725638,726592]]},"purl":{"exact":[["purL",0,"purL","NZ_QPEQ01000001.1",1772106,1776201]],"prefix":[]},"pbonn_03183_":{"exact":[],"prefix":["PBONN_03183_gene"]},"pbonn_01431_ge":{"prefix":["PBONN_01431_gene"],"exact":[]},"pbonn_02426":{"prefix":["PBONN_02426_gene"],"exact":[["PBONN_02426",0,"PBONN_02426_gene","NZ_QPEQ01000001.1",2714771,2715830]]},"pbonn_00307_ge":{"exact":[],"prefix":["PBONN_00307_gene"]},"pbonn_03088_gen":{"prefix":["PBONN_03088_gene"],"exact":[]},"pbonn_00911_gene":{"prefix":[],"exact":[["PBONN_00911_gene",0,"PBONN_00911_gene","NZ_QPEQ01000001.1",1031091,1031358]]},"pbonn_03317_":{"prefix":["PBONN_03317_gene"],"exact":[]},"pbonn_00581_ge":{"exact":[],"prefix":["PBONN_00581_gene"]},"pbonn_00246_ge":{"exact":[],"prefix":["PBONN_00246_gene"]},"at":{"exact":[],"prefix":["atpB","atpE","atpF","atpH","atpA","atpG","atpD","atpC"]},"pbonn_00613_gen":{"exact":[],"prefix":["PBONN_00613_gene"]},"pbonn_01707_":{"prefix":["PBONN_01707_gene"],"exact":[]},"pbonn_01886":{"exact":[["PBONN_01886",0,"PBONN_01886_gene","NZ_QPEQ01000001.1",2142262,2142748]],"prefix":["PBONN_01886_gene"]}}